README.rst
setup.py
oslo.config.comparator.egg-info/PKG-INFO
oslo.config.comparator.egg-info/SOURCES.txt
oslo.config.comparator.egg-info/dependency_links.txt
oslo.config.comparator.egg-info/entry_points.txt
oslo.config.comparator.egg-info/requires.txt
oslo.config.comparator.egg-info/top_level.txt
oslo_config_comparator/__init__.py
oslo_config_comparator/config.py
oslo_config_comparator/config_comparator.py