Metadata-Version: 1.2
Name: oslo.config.comparator
Version: 0.3
Summary: OpenStack configure file comparator.
Home-page: https://github.com/Xeite/oslo.config.comparator
Author: Yang Youseok
Author-email: ileixe@gmail.com
License: MIT
Keywords: OpenStack oslo.config
Platform: UNKNOWN
Classifier: Development Status :: 3 - Alpha
Classifier: License :: OSI Approved :: MIT License
Classifier: Programming Language :: Python :: 3.6
Requires-Python: >=3.6
